cli/__init__.py
runeq/__init__.py
runeq/config.py
runeq/errors.py
runeq/resources/__init__.py
runeq/resources/client.py
runeq/resources/common.py
runeq/resources/event.py
runeq/resources/internal.py
runeq/resources/org.py
runeq/resources/patient.py
runeq/resources/project.py
runeq/resources/sleep.py
runeq/resources/stream.py
runeq/resources/stream_metadata.py
runeq/resources/user.py
runeq-0.17.7.dist-info/licenses/LICENSE
tests/__init__.py
tests/test_config.py
tests/resources/__init__.py
tests/resources/test_client.py
tests/resources/test_common.py
tests/resources/test_event.py
tests/resources/test_org.py
tests/resources/test_patient.py
tests/resources/test_project.py
tests/resources/test_sleep.py
tests/resources/test_stream.py
tests/resources/test_stream_metadata.py
tests/resources/test_user.py
runeq-0.17.7.dist-info/METADATA
runeq-0.17.7.dist-info/WHEEL
runeq-0.17.7.dist-info/entry_points.txt
runeq-0.17.7.dist-info/top_level.txt
runeq-0.17.7.dist-info/RECORD
