Metadata-Version: 2.4
Name: runeq
Version: 0.17.7
Summary: Query data from Rune Labs APIs
Home-page: https://github.com/rune-labs/runeq-python
Author: Rune Labs
Maintainer-email: support@runelabs.io
Keywords: rune labs api query data
Classifier: License :: OSI Approved :: MIT License
Classifier: Operating System :: OS Independent
Classifier: Programming Language :: Python :: 3 :: Only
Classifier: Programming Language :: Python :: 3.8
Classifier: Programming Language :: Python :: 3.9
Classifier: Programming Language :: Python :: 3.10
Classifier: Programming Language :: Python :: 3.11
Classifier: Programming Language :: Python :: 3.12
License-File: LICENSE
Requires-Dist: boto3>=1.23.0
Requires-Dist: click>=7.1
Requires-Dist: gql[requests]>=3.5.0
Requires-Dist: numpy>=1.18.2
Requires-Dist: PyYAML>=5.3.1
Requires-Dist: requests>=2.23.0
Requires-Dist: pandas>=1.1.5
Dynamic: author
Dynamic: classifier
Dynamic: description
Dynamic: description-content-type
Dynamic: home-page
Dynamic: keywords
Dynamic: license-file
Dynamic: maintainer-email
Dynamic: requires-dist
Dynamic: summary
